[{"id":3,"title":"wdsd","description":"sadasd"},{"id":4,"title":"dsdasd","description":"sadasdas"},{"id":5,"title":"dsdasd","description":"sadasdas"},{"id":6,"title":"dsdasd","description":"sadasdas"},{"id":7,"title":"dsdasd","description":"sadasdas"},{"id":8,"title":"dsdasd","description":"sadasdas"},{"id":9,"title":"dsdasd","description":"sadasdas"},{"id":10,"title":"dsdasd","description":"sadasdas"},{"id":11,"title":"dsdasd","description":"sadasdas"},{"id":12,"title":"dsdasd","description":"sadasdas"},{"id":13,"title":"dsdasd","description":"sadasdas"},{"id":14,"title":"dsdasd","description":"sadasdas"},{"id":15,"title":"dsdasd","description":"sadasdas"},{"id":16,"title":"dsdasd","description":"sadasdas"},{"id":17,"title":"dsdasd","description":"sadasdas"},{"id":18,"title":"dsdasd","description":"sadasdas"},{"id":19,"title":"dsdasd","description":"sadasdas"},{"id":20,"title":"dsdasd","description":"sadasdas"},{"id":21,"title":"dsdasd","description":"sadasdas"},{"id":22,"title":"dsdasd","description":"sadasdas"},{"id":23,"title":"dsdasd","description":"sadasdas"},{"id":24,"title":"dsdasd","description":"sadasdas"},{"id":25,"title":"dsdasd","description":"sadasdas"},{"id":26,"title":"dsdasd","description":"sadasdas"},{"id":27,"title":"dsdasd","description":"sadasdas"},{"id":28,"title":"dsdasd","description":"sadasdas"}]